iljicevs_ml/__init__.py
iljicevs_ml/auto_adaptive.py
iljicevs_ml/causal_model.py
iljicevs_ml/hybrid_model_with_improvements.py
iljicevs_ml/iljicevs_model.py
iljicevs_ml/model_tuner.py
iljicevs_ml/progressive_model.py
iljicevs_ml/utils.py
iljicevs_ml-0.2.7.dist-info/LICENSE
iljicevs_ml-0.2.7.dist-info/METADATA
iljicevs_ml-0.2.7.dist-info/WHEEL
iljicevs_ml-0.2.7.dist-info/top_level.txt
iljicevs_ml-0.2.7.dist-info/RECORD
