Metadata-Version: 2.1
Name: iljicevs-ml
Version: 0.2.7
Summary: Library implementation of the Iljiceva model.
Home-page: https://github.com/ilyacartwright/iljicevs_ml
Author: Mihails Iljicevs
Author-email: goenzi61@gmail.com
License: UNKNOWN
Platform: UNKNOWN
Classifier: Programming Language :: Python :: 3
Classifier: License :: OSI Approved :: MIT License
Classifier: Operating System :: OS Independent
Requires-Python: >=3.6
Requires-Dist: numpy
Requires-Dist: scikit-learn
Requires-Dist: matplotlib
Requires-Dist: hyperopt
Requires-Dist: imblearn
Requires-Dist: seaborn
Requires-Dist: tpot
Requires-Dist: python-docx
Requires-Dist: openpyxl
Requires-Dist: torch
Requires-Dist: causalml
Requires-Dist: pandas
